{"1": {"laptop": "labeled_metadata/1/laptop.json", "camera": "labeled_metadata/1/camera.json", "bus": "labeled_metadata/1/bus.json", "sweater": "labeled_metadata/1/sweater.json", "dress": "labeled_metadata/1/dress.json", "racing": "labeled_metadata/1/racing.json", "hockey": "labeled_metadata/1/hockey.json", "cosplay": "labeled_metadata/1/cosplay.json", "baseball": "labeled_metadata/1/baseball.json", "soccer": "labeled_metadata/1/soccer.json", "BACKGROUND": "labeled_metadata/1/BACKGROUND.json"}, "2": {"laptop": "labeled_metadata/2/laptop.json", "camera": "labeled_metadata/2/camera.json", "bus": "labeled_metadata/2/bus.json", "sweater": "labeled_metadata/2/sweater.json", "dress": "labeled_metadata/2/dress.json", "racing": "labeled_metadata/2/racing.json", "hockey": "labeled_metadata/2/hockey.json", "cosplay": "labeled_metadata/2/cosplay.json", "baseball": "labeled_metadata/2/baseball.json", "soccer": "labeled_metadata/2/soccer.json", "BACKGROUND": "labeled_metadata/2/BACKGROUND.json"}, "3": {"laptop": "labeled_metadata/3/laptop.json", "camera": "labeled_metadata/3/camera.json", "bus": "labeled_metadata/3/bus.json", "sweater": "labeled_metadata/3/sweater.json", "dress": "labeled_metadata/3/dress.json", "racing": "labeled_metadata/3/racing.json", "hockey": "labeled_metadata/3/hockey.json", "cosplay": "labeled_metadata/3/cosplay.json", "baseball": "labeled_metadata/3/baseball.json", "soccer": "labeled_metadata/3/soccer.json", "BACKGROUND": "labeled_metadata/3/BACKGROUND.json"}, "4": {"laptop": "labeled_metadata/4/laptop.json", "camera": "labeled_metadata/4/camera.json", "bus": "labeled_metadata/4/bus.json", "sweater": "labeled_metadata/4/sweater.json", "dress": "labeled_metadata/4/dress.json", "racing": "labeled_metadata/4/racing.json", "hockey": "labeled_metadata/4/hockey.json", "cosplay": "labeled_metadata/4/cosplay.json", "baseball": "labeled_metadata/4/baseball.json", "soccer": "labeled_metadata/4/soccer.json", "BACKGROUND": "labeled_metadata/4/BACKGROUND.json"}, "5": {"laptop": "labeled_metadata/5/laptop.json", "camera": "labeled_metadata/5/camera.json", "bus": "labeled_metadata/5/bus.json", "sweater": "labeled_metadata/5/sweater.json", "dress": "labeled_metadata/5/dress.json", "racing": "labeled_metadata/5/racing.json", "hockey": "labeled_metadata/5/hockey.json", "cosplay": "labeled_metadata/5/cosplay.json", "baseball": "labeled_metadata/5/baseball.json", "soccer": "labeled_metadata/5/soccer.json", "BACKGROUND": "labeled_metadata/5/BACKGROUND.json"}, "6": {"laptop": "labeled_metadata/6/laptop.json", "camera": "labeled_metadata/6/camera.json", "bus": "labeled_metadata/6/bus.json", "sweater": "labeled_metadata/6/sweater.json", "dress": "labeled_metadata/6/dress.json", "racing": "labeled_metadata/6/racing.json", "hockey": "labeled_metadata/6/hockey.json", "cosplay": "labeled_metadata/6/cosplay.json", "baseball": "labeled_metadata/6/baseball.json", "soccer": "labeled_metadata/6/soccer.json", "BACKGROUND": "labeled_metadata/6/BACKGROUND.json"}, "7": {"laptop": "labeled_metadata/7/laptop.json", "camera": "labeled_metadata/7/camera.json", "bus": "labeled_metadata/7/bus.json", "sweater": "labeled_metadata/7/sweater.json", "dress": "labeled_metadata/7/dress.json", "racing": "labeled_metadata/7/racing.json", "hockey": "labeled_metadata/7/hockey.json", "cosplay": "labeled_metadata/7/cosplay.json", "baseball": "labeled_metadata/7/baseball.json", "soccer": "labeled_metadata/7/soccer.json", "BACKGROUND": "labeled_metadata/7/BACKGROUND.json"}, "8": {"laptop": "labeled_metadata/8/laptop.json", "camera": "labeled_metadata/8/camera.json", "bus": "labeled_metadata/8/bus.json", "sweater": "labeled_metadata/8/sweater.json", "dress": "labeled_metadata/8/dress.json", "racing": "labeled_metadata/8/racing.json", "hockey": "labeled_metadata/8/hockey.json", "cosplay": "labeled_metadata/8/cosplay.json", "baseball": "labeled_metadata/8/baseball.json", "soccer": "labeled_metadata/8/soccer.json", "BACKGROUND": "labeled_metadata/8/BACKGROUND.json"}, "9": {"laptop": "labeled_metadata/9/laptop.json", "camera": "labeled_metadata/9/camera.json", "bus": "labeled_metadata/9/bus.json", "sweater": "labeled_metadata/9/sweater.json", "dress": "labeled_metadata/9/dress.json", "racing": "labeled_metadata/9/racing.json", "hockey": "labeled_metadata/9/hockey.json", "cosplay": "labeled_metadata/9/cosplay.json", "baseball": "labeled_metadata/9/baseball.json", "soccer": "labeled_metadata/9/soccer.json", "BACKGROUND": "labeled_metadata/9/BACKGROUND.json"}, "10": {"laptop": "labeled_metadata/10/laptop.json", "camera": "labeled_metadata/10/camera.json", "bus": "labeled_metadata/10/bus.json", "sweater": "labeled_metadata/10/sweater.json", "dress": "labeled_metadata/10/dress.json", "racing": "labeled_metadata/10/racing.json", "hockey": "labeled_metadata/10/hockey.json", "cosplay": "labeled_metadata/10/cosplay.json", "baseball": "labeled_metadata/10/baseball.json", "soccer": "labeled_metadata/10/soccer.json", "BACKGROUND": "labeled_metadata/10/BACKGROUND.json"}}